Metadata-Version: 1.0
Name: PypiPackageExamplePedroOrtizPerez
Version: 0.0.1
Summary: paquete de pruebas
Home-page: https://github.com/peortizpe/PypiPackageExamplePedroOrtizPerez
Author: Pedro Ortiz Pérez
Author-email: UNKNOWN
License: MIT
Platform: UNKNOWN
